trio_serial_windows/__init__.py
trio_serial_windows/_windows.py
trio_serial_windows/_windows_cffi.py
trio_serial_windows-0.1.1.dist-info/LICENSE
trio_serial_windows-0.1.1.dist-info/METADATA
trio_serial_windows-0.1.1.dist-info/WHEEL
trio_serial_windows-0.1.1.dist-info/top_level.txt
trio_serial_windows-0.1.1.dist-info/RECORD
