Metadata-Version: 2.1
Name: trio-serial-windows
Version: 0.1.1
Summary: Serial Port support for python-trio on Windows
Project-URL: Homepage, https://github.com/clint-lawrence/trio-serial-windows
Requires-Python: >=3.8
License-File: LICENSE
Requires-Dist: trio-serial
Requires-Dist: trio
